[
  {
    "id": 201,
    "type": "大吉",
    "theme": "新たな挑戦",
    "color": "#4ecdc4",
    "message": "大きなチャンスが舞い込む日！",
    "description": "仕事面で新しいプロジェクトや役割を任されるかもしれません。自分の強みを活かして積極的に取り組むことで、周囲からの評価も高まります。苦手な分野にも思い切ってチャレンジし、同僚や上司と協力しながら新しいスキルを身につける絶好の機会です。",
    "advice": [
      "自分の意見やアイデアを積極的に発信しましょう。",
      "苦手な分野にも思い切ってチャレンジしてみましょう。",
      "同僚や上司との会話を増やし信頼関係を築きましょう。",
      "タスクの優先順位を明確にして効率よく進めましょう。",
      "新しいスキルの習得に時間を使うのもおすすめです。"
    ],
    "luck": {
      "creativity": "★★★★★",
      "teamwork": "★★★★☆",
      "leadership": "★★★★★",
      "efficiency": "★★★★☆"
    }
  },
  {
    "id": 202,
    "type": "中吉",
    "theme": "人間関係の改善",
    "color": "#4ecdc4",
    "message": "人とのコミュニケーションがカギ",
    "description": "人とのコミュニケーションを大切にすることで、運気がアップします。特に誤解を解くチャンスが訪れるでしょう。素直な気持ちを伝えたり、相手の話に耳を傾けることで信頼関係が深まり、職場の雰囲気も良くなります。",
    "advice": [
      "素直な気持ちを伝えることが大切です。",
      "相手の話に耳を傾けて理解を深めましょう。",
      "感謝の気持ちを言葉でしっかり伝えましょう。",
      "自分の考えを整理してから相手に伝えましょう。",
      "オープンな姿勢で接することで信頼が深まります。"
    ],
    "luck": {
      "creativity": "★★★★☆",
      "teamwork": "★★★★☆",
      "leadership": "★★★★☆",
      "efficiency": "★★★☆☆"
    }
  },
  {
    "id": 203,
    "type": "小吉",
    "theme": "安定した運営",
    "color": "#45b7d1",
    "message": "順調に物事が進む日",
    "description": "特に大きな変化はありませんが、日々の業務が順調に進むことでしょう。コツコツと積み上げてきたものが実を結びます。ルーチンワークを大切にし、同僚と協力し合うことで小さな成功体験を積み重ねられます。",
    "advice": [
      "ルーチンワークを大切にし着実にこなしていきましょう。",
      "小さな成功体験を積み重ねて自信をつけましょう。",
      "同僚と協力し合いチームワークを発揮しましょう。",
      "自分の成長を実感できるよう定期的に振り返りましょう。",
      "困ったときは周囲に相談し一人で抱え込まないように。"
    ],
    "luck": {
      "creativity": "★★★☆☆",
      "teamwork": "★★★☆☆",
      "leadership": "★★★☆☆",
      "efficiency": "★★★☆☆"
    }
  },
  {
    "id": 204,
    "type": "吉",
    "theme": "安定した成果",
    "color": "#45b7d1",
    "message": "着実な成果が期待できる日",
    "description": "日々の努力が実を結び、安定した成果が得られるでしょう。新しい挑戦よりも、今ある仕事に集中し、着実に進めることが大切です。周囲への感謝を忘れず、協力し合うことでさらに良い結果が得られます。",
    "advice": [
      "日々の努力を大切にし安定した成果を目指しましょう。",
      "今ある仕事に集中し着実に進めることが大切です。",
      "周囲への感謝を忘れず協力し合いましょう。",
      "新しい挑戦よりも現状維持を意識しましょう。",
      "小さな成功も見逃さず自分を褒めてあげましょう。"
    ],
    "luck": {
      "creativity": "★★★☆☆",
      "teamwork": "★★★★☆",
      "leadership": "★★★☆☆",
      "efficiency": "★★★★☆"
    }
  },
  {
    "id": 205,
    "type": "半吉",
    "theme": "計画的な行動",
    "color": "#ffe066",
    "message": "計画的な行動が吉",
    "description": "欲張らず、計画的に進めることで安定した結果が得られます。焦らず一歩ずつ目標に向かって進むことで、安心感と達成感を得られます。困ったときは信頼できる人に相談し、無理をせず自分のペースを守りましょう。",
    "advice": [
      "本当に必要なことかどうか一晩考えてから決めましょう。",
      "計画的に行動することで安定した結果が得られます。",
      "焦らず一歩ずつ進めることを意識しましょう。",
      "無理をせず自分のペースで取り組みましょう。",
      "困ったときは信頼できる人に相談してみましょう。"
    ],
    "luck": {
      "creativity": "★★☆☆☆",
      "teamwork": "★★★☆☆",
      "leadership": "★★☆☆☆",
      "efficiency": "★★★☆☆"
    }
  },
  {
    "id": 206,
    "type": "末吉",
    "theme": "予想外の課題",
    "color": "#ffd700",
    "message": "思わぬ課題に注意",
    "description": "急な課題が発生しやすい日です。余裕を持った行動が大切です。日頃から準備をしておくとトラブルにも強くなれます。困ったときは一人で抱え込まず、周囲に相談して冷静に対応しましょう。",
    "advice": [
      "急な課題にも慌てず冷静に対応することが大切です。",
      "日頃から準備をしておくとトラブルにも強くなれます。",
      "困ったときは一人で抱え込まず周囲に相談しましょう。",
      "余裕を持ったスケジュールで行動しましょう。",
      "体調管理にも気を配り無理をしないようにしましょう。"
    ],
    "luck": {
      "creativity": "★★☆☆☆",
      "teamwork": "★★☆☆☆",
      "leadership": "★★★☆☆",
      "efficiency": "★★☆☆☆"
    }
  },
  {
    "id": 207,
    "type": "凶",
    "theme": "ミス・トラブル",
    "color": "#ffb347",
    "message": "ミスに注意",
    "description": "気が緩みやすく、ミスやトラブルが起こりやすい日です。タスク管理を徹底し、優先順位を明確にすることで被害を最小限に抑えられます。無理に一人で抱え込まず、周囲に相談して助けを求めましょう。",
    "advice": [
      "タスク管理を徹底し優先順位を明確にしましょう。",
      "ミスが起きたら冷静に原因を分析しましょう。",
      "無理に一人で抱え込まず周囲に相談しましょう。",
      "休息をとって心身のバランスを整えましょう。",
      "焦らず慎重に行動することが大切です。"
    ],
    "luck": {
      "creativity": "★☆☆☆☆",
      "teamwork": "★★☆☆☆",
      "leadership": "★★☆☆☆",
      "efficiency": "★☆☆☆☆"
    }
  },
  {
    "id": 208,
    "type": "大凶",
    "theme": "大きな失敗・注意",
    "color": "#ff4757",
    "message": "大きな失敗に注意が必要です",
    "description": "大きな失敗やトラブルに注意が必要な日です。うまい話には裏があることが多いので、慎重に判断し、焦らず冷静に行動することが大切です。失敗を恐れず、次に活かす気持ちを持ちましょう。",
    "advice": [
      "うまい話には裏があることが多いので慎重に判断しましょう。",
      "大きな決断は焦らず時間をかけて考えましょう。",
      "困ったときは信頼できる人に相談してみてください。",
      "失敗を恐れず次に活かす気持ちを持ちましょう。",
      "自分の気持ちを大切にし無理をしないようにしましょう。"
    ],
    "luck": {
      "creativity": "★☆☆☆☆",
      "teamwork": "★☆☆☆☆",
      "leadership": "★☆☆☆☆",
      "efficiency": "★☆☆☆☆"
    }
  }
]
