{
  "categories": {
    "general": {
      "name": "総合運",
      "icon": "fas fa-star",
      "color": "#667eea",
      "description": "今日の全体的な運勢を占います"
    },
    "love": {
      "name": "恋愛運",
      "icon": "fas fa-heart",
      "color": "#ff6b9d",
      "description": "恋愛に関する運勢を占います"
    },
    "money": {
      "name": "金運",
      "icon": "fas fa-coins",
      "color": "#ffd700",
      "description": "お金に関する運勢を占います"
    },
    "work": {
      "name": "仕事運",
      "icon": "fas fa-briefcase",
      "color": "#4ecdc4",
      "description": "仕事やキャリアに関する運勢を占います"
    },
    "health": {
      "name": "健康運",
      "icon": "fas fa-leaf",
      "color": "#95e1d3",
      "description": "健康に関する運勢を占います"
    },
    "study": {
      "name": "学業運",
      "icon": "fas fa-graduation-cap",
      "color": "#a8e6cf",
      "description": "学習や試験に関する運勢を占います"
    }
  },
  "fortunes": {
    "general": [
      {
        "id": 1,
        "type": "大吉",
        "color": "#ff6b6b",
        "message": "今日は最高の一日になるでしょう！",
        "description": "すべてのことが順調に進み、素晴らしい出会いや機会に恵まれます。積極的に行動することで、さらなる幸運を引き寄せることができるでしょう。",
        "advice": [
          "今日は何事にも前向きに取り組みましょう。",
          "新しいことにチャレンジするのに最適な日です。",
          "周りの人への感謝の気持ちを忘れずに。"
        ],
        "luck": {
          "love": "★★★★★",
          "money": "★★★★★",
          "health": "★★★★★",
          "work": "★★★★★"
        }
      },
      {
        "id": 2,
        "type": "中吉",
        "color": "#4ecdc4",
        "message": "良いことが起こりそうな予感です",
        "description": "全体的に運気は好調です。小さな幸せを見つけることができ、周囲の人々との関係も良好になるでしょう。",
        "advice": [
          "今日は周りの人に優しさを示すことで、より良い一日になるでしょう。",
          "小さな成功を積み重ねることが大切です。"
        ],
        "luck": {
          "love": "★★★★☆",
          "money": "★★★☆☆",
          "health": "★★★★☆",
          "work": "★★★★☆"
        }
      },
      {
        "id": 3,
        "type": "小吉",
        "color": "#45b7d1",
        "message": "穏やかで安定した一日になりそうです",
        "description": "大きな変化はありませんが、平穏で心地よい時間を過ごせるでしょう。身近な人との時間を大切にしてください。",
        "advice": [
          "今日は無理をせず、自分のペースで過ごすことが大切です。",
          "家族や友人との時間を大切にしましょう。"
        ],
        "luck": {
          "love": "★★★☆☆",
          "money": "★★☆☆☆",
          "health": "★★★☆☆",
          "work": "★★★☆☆"
        }
      }
    ],
    "love": [
      {
        "id": 11,
        "type": "恋愛大吉",
        "color": "#ff6b9d",
        "message": "運命の出会いが待っています！",
        "description": "今日は恋愛において最高の日です。新しい出会いや、既存の関係の進展が期待できます。",
        "advice": [
          "積極的にコミュニケーションを取りましょう。",
          "自分らしさを大切にして。",
          "相手の気持ちを尊重することが大切です。"
        ],
        "luck": {
          "attraction": "★★★★★",
          "communication": "★★★★★",
          "harmony": "★★★★☆",
          "passion": "★★★★★"
        }
      },
      {
        "id": 12,
        "type": "恋愛中吉",
        "color": "#ffa8cc",
        "message": "心温まる時間が過ごせそうです",
        "description": "恋愛面で穏やかな幸せを感じられる日です。大切な人との絆が深まるでしょう。",
        "advice": [
          "素直な気持ちを伝えることが大切です。",
          "小さな思いやりが大きな愛を育みます。"
        ],
        "luck": {
          "attraction": "★★★★☆",
          "communication": "★★★☆☆",
          "harmony": "★★★★★",
          "passion": "★★★☆☆"
        }
      }
    ],
    "money": [
      {
        "id": 21,
        "type": "金運大吉",
        "color": "#ffd700",
        "message": "思わぬ収入があるかもしれません！",
        "description": "金運が非常に良い日です。投資や買い物、副業などで良い結果が期待できます。",
        "advice": [
          "計画的な支出を心がけましょう。",
          "新しい投資機会を検討してみて。",
          "節約の工夫を考えてみましょう。"
        ],
        "luck": {
          "income": "★★★★★",
          "investment": "★★★★☆",
          "savings": "★★★★★",
          "spending": "★★★☆☆"
        }
      },
      {
        "id": 22,
        "type": "金運中吉",
        "color": "#ffed4e",
        "message": "堅実な財務管理が実を結びます",
        "description": "今までの努力が金銭面で報われる兆しが見えています。着実な成果が期待できます。",
        "advice": [
          "無駄遣いを控えて堅実に。",
          "長期的な視点で資産形成を。"
        ],
        "luck": {
          "income": "★★★☆☆",
          "investment": "★★★☆☆",
          "savings": "★★★★☆",
          "spending": "★★★★☆"
        }
      }
    ],
    "work": [
      {
        "id": 31,
        "type": "仕事大吉",
        "color": "#4ecdc4",
        "message": "大きなチャンスが舞い込みそうです！",
        "description": "仕事面で素晴らしい機会に恵まれる日です。新しいプロジェクトや昇進のチャンスがあるかもしれません。",
        "advice": [
          "積極的に提案や意見を述べましょう。",
          "チームワークを大切に。",
          "新しいスキルを学ぶ絶好の機会です。"
        ],
        "luck": {
          "creativity": "★★★★★",
          "teamwork": "★★★★☆",
          "leadership": "★★★★★",
          "efficiency": "★★★★☆"
        }
      }
    ],
    "health": [
      {
        "id": 41,
        "type": "健康大吉",
        "color": "#95e1d3",
        "message": "体も心も絶好調です！",
        "description": "健康面で非常に良いコンディションです。新しい運動や健康習慣を始めるのに最適な日です。",
        "advice": [
          "適度な運動を心がけましょう。",
          "バランスの取れた食事を。",
          "十分な睡眠と休息を取って。"
        ],
        "luck": {
          "energy": "★★★★★",
          "immunity": "★★★★☆",
          "mental": "★★★★★",
          "vitality": "★★★★☆"
        }
      }
    ],
    "study": [
      {
        "id": 51,
        "type": "学業大吉",
        "color": "#a8e6cf",
        "message": "集中力が冴えて効率的に学習できます！",
        "description": "学習面で最高のコンディションです。新しい知識の習得や試験勉強が捗るでしょう。",
        "advice": [
          "計画的に学習スケジュールを立てましょう。",
          "積極的に質問や議論をして。",
          "復習の時間も大切にしましょう。"
        ],
        "luck": {
          "concentration": "★★★★★",
          "memory": "★★★★☆",
          "understanding": "★★★★★",
          "motivation": "★★★★☆"
        }
      }
    ]
  },
  "specialMessages": [
    "心を込めておみくじを引いてください",
    "今日一日が素晴らしい日になりますように",
    "あなたの幸運を祈っています",
    "運命の扉が開かれようとしています",
    "新しい発見があなたを待っています"
  ]
}
